neptune_pytorch/__init__.py
neptune_pytorch/impl/__init__.py
neptune_pytorch/impl/_torchwatcher.py
neptune_pytorch/impl/version.py
neptune_pytorch-3.0.0.dist-info/METADATA
neptune_pytorch-3.0.0.dist-info/WHEEL
neptune_pytorch-3.0.0.dist-info/licenses/LICENSE
neptune_pytorch-3.0.0.dist-info/RECORD
