Metadata-Version: 2.4
Name: neptune-pytorch
Version: 3.0.0
Summary: neptune.ai pytorch integration library
License: Apache-2.0
License-File: LICENSE
Keywords: MLOps,ML Experiment Tracking,ML Model Registry,ML Model Store,ML Metadata Store,PyTorch
Author: neptune.ai
Author-email: contact@neptune.ai
Requires-Python: >=3.10,<4.0
Classifier: Development Status :: 5 - Production/Stable
Classifier: Environment :: Console
Classifier: Intended Audience :: Developers
Classifier: Intended Audience :: Science/Research
Classifier: License :: OSI Approved :: Apache Software License
Classifier: Natural Language :: English
Classifier: Operating System :: MacOS
Classifier: Operating System :: Microsoft :: Windows
Classifier: Operating System :: POSIX
Classifier: Operating System :: Unix
Classifier: Programming Language :: Python :: 3
Classifier: Programming Language :: Python :: 3.10
Classifier: Programming Language :: Python :: 3.11
Classifier: Programming Language :: Python :: 3.12
Classifier: Programming Language :: Python :: 3.13
Classifier: Programming Language :: Python :: 3.14
Classifier: Programming Language :: Python :: Implementation :: CPython
Classifier: Topic :: Scientific/Engineering :: Artificial Intelligence
Classifier: Topic :: Software Development :: Libraries :: Python Modules
Provides-Extra: dev
Requires-Dist: neptune_scale (>=0.14.0)
Requires-Dist: numpy (>=1.20.0)
Requires-Dist: pre-commit ; extra == "dev"
Requires-Dist: pydot ; extra == "dev"
Requires-Dist: pytest (>=5.0) ; extra == "dev"
Requires-Dist: pytest-cov (==2.10.1) ; extra == "dev"
Requires-Dist: torch (>=1.11.0)
Requires-Dist: torchviz ; extra == "dev"
Project-URL: Documentation, https://docs.neptune.ai
Project-URL: Homepage, https://neptune.ai/
Project-URL: Repository, https://github.com/neptune-ai/neptune-pytorch
Project-URL: Tracker, https://github.com/neptune-ai/neptune-pytorch/issues
